{
  "128": [
    {
      "N": 128,
      "rho": 0.4,
      "ku": 26,
      "kv": 51,
      "Ru": 0.203125,
      "Rv": 0.3984375,
      "sum_rate": 0.6015625,
      "nn_bler": 0.0,
      "sc_bler": 0.003,
      "ratio": null,
      "n_cw": 5000,
      "time_nn_sec": 18.536180374969263,
      "time_sc_sec": 0.9152241250267252
    },
    {
      "N": 128,
      "rho": 0.5,
      "ku": 32,
      "kv": 64,
      "Ru": 0.25,
      "Rv": 0.5,
      "sum_rate": 0.75,
      "nn_bler": 0.0,
      "sc_bler": 0.0072,
      "ratio": null,
      "n_cw": 5000,
      "time_nn_sec": 19.204166333947796,
      "time_sc_sec": 0.937241375038866
    },
    {
      "N": 128,
      "rho": 0.6,
      "ku": 38,
      "kv": 77,
      "Ru": 0.296875,
      "Rv": 0.6015625,
      "sum_rate": 0.8984375,
      "nn_bler": 0.0004,
      "sc_bler": 0.0244,
      "ratio": 0.01639344262295082,
      "n_cw": 5000,
      "time_nn_sec": 17.739188500039745,
      "time_sc_sec": 0.917737916985061
    },
    {
      "N": 128,
      "rho": 0.7,
      "ku": 45,
      "kv": 90,
      "Ru": 0.3515625,
      "Rv": 0.703125,
      "sum_rate": 1.0546875,
      "nn_bler": 0.0042,
      "sc_bler": 0.1312,
      "ratio": 0.03201219512195121,
      "n_cw": 5000,
      "time_nn_sec": 18.132836999953724,
      "time_sc_sec": 0.9443885000073351
    },
    {
      "N": 128,
      "rho": 0.8,
      "ku": 51,
      "kv": 102,
      "Ru": 0.3984375,
      "Rv": 0.796875,
      "sum_rate": 1.1953125,
      "nn_bler": 0.1544,
      "sc_bler": 0.3328,
      "ratio": 0.46394230769230776,
      "n_cw": 5000,
      "time_nn_sec": 18.327461541979574,
      "time_sc_sec": 0.9530530829797499
    },
    {
      "N": 128,
      "rho": 0.9,
      "ku": 58,
      "kv": 115,
      "Ru": 0.453125,
      "Rv": 0.8984375,
      "sum_rate": 1.3515625,
      "nn_bler": 0.8124,
      "sc_bler": 0.635,
      "ratio": 1.2793700787401574,
      "n_cw": 5000,
      "time_nn_sec": 18.582831333973445,
      "time_sc_sec": 0.9471346249920316
    }
  ],
  "256": [
    {
      "N": 256,
      "rho": 0.4,
      "ku": 51,
      "kv": 102,
      "Ru": 0.19921875,
      "Rv": 0.3984375,
      "sum_rate": 0.59765625,
      "nn_bler": 0.0,
      "sc_bler": 0.0,
      "ratio": null,
      "n_cw": 5000,
      "time_nn_sec": 49.57291604101192,
      "time_sc_sec": 3.2018912920029834
    },
    {
      "N": 256,
      "rho": 0.5,
      "ku": 64,
      "kv": 128,
      "Ru": 0.25,
      "Rv": 0.5,
      "sum_rate": 0.75,
      "nn_bler": 0.0,
      "sc_bler": 0.002,
      "ratio": null,
      "n_cw": 5000,
      "time_nn_sec": 51.516473083989695,
      "time_sc_sec": 3.1650554169900715
    },
    {
      "N": 256,
      "rho": 0.6,
      "ku": 77,
      "kv": 154,
      "Ru": 0.30078125,
      "Rv": 0.6015625,
      "sum_rate": 0.90234375,
      "nn_bler": 0.0002,
      "sc_bler": 0.0122,
      "ratio": 0.01639344262295082,
      "n_cw": 5000,
      "time_nn_sec": 52.26934554101899,
      "time_sc_sec": 3.2002941250102594
    },
    {
      "N": 256,
      "rho": 0.7,
      "ku": 90,
      "kv": 179,
      "Ru": 0.3515625,
      "Rv": 0.69921875,
      "sum_rate": 1.05078125,
      "nn_bler": 0.0056,
      "sc_bler": 0.0866,
      "ratio": 0.06466512702078522,
      "n_cw": 5000,
      "time_nn_sec": 53.01902050001081,
      "time_sc_sec": 3.2825429160147905
    },
    {
      "N": 256,
      "rho": 0.8,
      "ku": 102,
      "kv": 205,
      "Ru": 0.3984375,
      "Rv": 0.80078125,
      "sum_rate": 1.19921875,
      "nn_bler": 0.194,
      "sc_bler": 0.331,
      "ratio": 0.5861027190332326,
      "n_cw": 5000,
      "time_nn_sec": 52.99507004197221,
      "time_sc_sec": 3.3268754170276225
    },
    {
      "N": 256,
      "rho": 0.9,
      "ku": 115,
      "kv": 230,
      "Ru": 0.44921875,
      "Rv": 0.8984375,
      "sum_rate": 1.34765625,
      "nn_bler": 0.9548,
      "sc_bler": 0.7174,
      "ratio": 1.330917201003624,
      "n_cw": 5000,
      "time_nn_sec": 59.81850941700395,
      "time_sc_sec": 3.3596366249839775
    }
  ],
  "64": [
    {
      "N": 64,
      "rho": 0.4,
      "ku": 13,
      "kv": 26,
      "Ru": 0.203125,
      "Rv": 0.40625,
      "sum_rate": 0.609375,
      "nn_bler": 0.0002,
      "sc_bler": 0.0202,
      "ratio": 0.009900990099009901,
      "n_cw": 5000,
      "time_nn_sec": 5.804724459012505,
      "time_sc_sec": 0.34268583299126476
    },
    {
      "N": 64,
      "rho": 0.5,
      "ku": 16,
      "kv": 32,
      "Ru": 0.25,
      "Rv": 0.5,
      "sum_rate": 0.75,
      "nn_bler": 0.0,
      "sc_bler": 0.0162,
      "ratio": null,
      "n_cw": 5000,
      "time_nn_sec": 5.972484291996807,
      "time_sc_sec": 0.3486904589808546
    },
    {
      "N": 64,
      "rho": 0.6,
      "ku": 19,
      "kv": 38,
      "Ru": 0.296875,
      "Rv": 0.59375,
      "sum_rate": 0.890625,
      "nn_bler": 0.002,
      "sc_bler": 0.0572,
      "ratio": 0.03496503496503497,
      "n_cw": 5000,
      "time_nn_sec": 6.0756162499892525,
      "time_sc_sec": 0.40959958400344476
    },
    {
      "N": 64,
      "rho": 0.7,
      "ku": 22,
      "kv": 45,
      "Ru": 0.34375,
      "Rv": 0.703125,
      "sum_rate": 1.046875,
      "nn_bler": 0.0098,
      "sc_bler": 0.129,
      "ratio": 0.07596899224806201,
      "n_cw": 5000,
      "time_nn_sec": 6.534212208993267,
      "time_sc_sec": 0.5129769999766722
    },
    {
      "N": 64,
      "rho": 0.8,
      "ku": 26,
      "kv": 51,
      "Ru": 0.40625,
      "Rv": 0.796875,
      "sum_rate": 1.203125,
      "nn_bler": 0.1176,
      "sc_bler": 0.3184,
      "ratio": 0.3693467336683417,
      "n_cw": 5000,
      "time_nn_sec": 7.8058067499659956,
      "time_sc_sec": 0.5763340829871595
    },
    {
      "N": 64,
      "rho": 0.9,
      "ku": 29,
      "kv": 58,
      "Ru": 0.453125,
      "Rv": 0.90625,
      "sum_rate": 1.359375,
      "nn_bler": 0.614,
      "sc_bler": 0.5232,
      "ratio": 1.1735474006116209,
      "n_cw": 5000,
      "time_nn_sec": 7.2328733340254985,
      "time_sc_sec": 0.49397433298872784
    }
  ],
  "512": [
    {
      "N": 512,
      "rho": 0.4,
      "ku": 102,
      "kv": 205,
      "Ru": 0.19921875,
      "Rv": 0.400390625,
      "sum_rate": 0.599609375,
      "nn_bler": 0.0,
      "sc_bler": 0.0,
      "ratio": null,
      "n_cw": 3000,
      "time_nn_sec": 110.89365741598886,
      "time_sc_sec": 7.758892334008124
    },
    {
      "N": 512,
      "rho": 0.5,
      "ku": 128,
      "kv": 256,
      "Ru": 0.25,
      "Rv": 0.5,
      "sum_rate": 0.75,
      "nn_bler": 0.0003333333333333333,
      "sc_bler": 0.0,
      "ratio": null,
      "n_cw": 3000,
      "time_nn_sec": 115.26644616696285,
      "time_sc_sec": 7.882407207973301
    },
    {
      "N": 512,
      "rho": 0.6,
      "ku": 154,
      "kv": 307,
      "Ru": 0.30078125,
      "Rv": 0.599609375,
      "sum_rate": 0.900390625,
      "nn_bler": 0.0,
      "sc_bler": 0.003,
      "ratio": null,
      "n_cw": 3000,
      "time_nn_sec": 121.3844238340389,
      "time_sc_sec": 8.163409250031691
    },
    {
      "N": 512,
      "rho": 0.7,
      "ku": 179,
      "kv": 358,
      "Ru": 0.349609375,
      "Rv": 0.69921875,
      "sum_rate": 1.048828125,
      "nn_bler": 0.004,
      "sc_bler": 0.04766666666666667,
      "ratio": 0.0839160839160839,
      "n_cw": 3000,
      "time_nn_sec": 121.21308729198063,
      "time_sc_sec": 7.977831791038625
    },
    {
      "N": 512,
      "rho": 0.8,
      "ku": 205,
      "kv": 410,
      "Ru": 0.400390625,
      "Rv": 0.80078125,
      "sum_rate": 1.201171875,
      "nn_bler": 0.2733333333333333,
      "sc_bler": 0.318,
      "ratio": 0.8595387840670858,
      "n_cw": 3000,
      "time_nn_sec": 122.89224454096984,
      "time_sc_sec": 8.425718542013783
    },
    {
      "N": 512,
      "rho": 0.9,
      "ku": 230,
      "kv": 461,
      "Ru": 0.44921875,
      "Rv": 0.900390625,
      "sum_rate": 1.349609375,
      "nn_bler": 0.9953333333333333,
      "sc_bler": 0.8023333333333333,
      "ratio": 1.2405484004985459,
      "n_cw": 3000,
      "time_nn_sec": 123.85430875001475,
      "time_sc_sec": 8.388810792006552
    }
  ]
}